rtctools_hydraulic_structures/__init__.py
rtctools_hydraulic_structures/_version.py
rtctools_hydraulic_structures/orifice_mixin.py
rtctools_hydraulic_structures/polygon_enclosure.py
rtctools_hydraulic_structures/pumping_station_mixin.py
rtctools_hydraulic_structures/util.py
rtctools_hydraulic_structures/weir_mixin.py
rtctools_hydraulic_structures/modelica/Deltares/HydraulicStructures/package.mo
rtctools_hydraulic_structures/modelica/Deltares/HydraulicStructures/Orifice/Orifice.mo
rtctools_hydraulic_structures/modelica/Deltares/HydraulicStructures/Orifice/package.mo
rtctools_hydraulic_structures/modelica/Deltares/HydraulicStructures/PumpingStation/Pump.mo
rtctools_hydraulic_structures/modelica/Deltares/HydraulicStructures/PumpingStation/PumpingStation.mo
rtctools_hydraulic_structures/modelica/Deltares/HydraulicStructures/PumpingStation/Resistance.mo
rtctools_hydraulic_structures/modelica/Deltares/HydraulicStructures/PumpingStation/package.mo
rtctools_hydraulic_structures/modelica/Deltares/HydraulicStructures/Weir/Weir.mo
rtctools_hydraulic_structures/modelica/Deltares/HydraulicStructures/Weir/package.mo
rtc_tools_hydraulic_structures-2.0.0a18.dist-info/COPYING.LESSER
rtc_tools_hydraulic_structures-2.0.0a18.dist-info/METADATA
rtc_tools_hydraulic_structures-2.0.0a18.dist-info/WHEEL
rtc_tools_hydraulic_structures-2.0.0a18.dist-info/entry_points.txt
rtc_tools_hydraulic_structures-2.0.0a18.dist-info/top_level.txt
rtc_tools_hydraulic_structures-2.0.0a18.dist-info/RECORD
