Metadata-Version: 2.1
Name: rtc-tools-hydraulic-structures
Version: 2.0.0a18
Summary: Hydraulic structures models for RTC-Tools 2.
Home-page: http://www.deltares.nl/en/software/rtc-tools/
Author: Deltares
Maintainer: Deltares
License: LGPLv3
Keywords: rtctools optimization weir pump
Platform: Windows
Platform: Linux
Platform: Mac OS-X
Platform: Unix
Classifier: Development Status :: 4 - Beta
Classifier: Intended Audience :: Science/Research
Classifier: Intended Audience :: Information Technology
Classifier: License :: OSI Approved :: GNU Lesser General Public License v3 (LGPLv3)
Classifier: Programming Language :: Other
Classifier: Topic :: Scientific/Engineering :: GIS
Classifier: Topic :: Scientific/Engineering :: Mathematics
Classifier: Topic :: Scientific/Engineering :: Physics
Classifier: Operating System :: Microsoft :: Windows
Classifier: Operating System :: POSIX
Classifier: Operating System :: Unix
Classifier: Operating System :: MacOS
Requires-Python: >=3.8
Requires-Dist: casadi>=3.5
Requires-Dist: rtc-tools>=2.4.0a6
Requires-Dist: rtc-tools-channel-flow>=1.1
